saxo_apy/__init__.py
saxo_apy/client.py
saxo_apy/models.py
saxo_apy/redirect_server.py
saxo_apy/utils.py
saxo_apy/version.py
saxo_apy-0.2.8.dist-info/METADATA
saxo_apy-0.2.8.dist-info/WHEEL
saxo_apy-0.2.8.dist-info/licenses/LICENSE
saxo_apy-0.2.8.dist-info/RECORD
