Metadata-Version: 2.1
Name: saxo-apy
Version: 0.2.8
Summary: A lightweight Python client for hassle-free tinkering with Saxo OpenAPI.
Author-email: Gid <giddevanderven@gmail.com>
License: MIT
License-File: LICENSE
Requires-Python: >=3.8
Requires-Dist: flask==2.3.3
Requires-Dist: httpx==0.24.1
Requires-Dist: loguru==0.7.0
Requires-Dist: pydantic==1.10.12
Requires-Dist: websockets==11.0.3
